jupytercad_app/__init__.py
jupytercad_app/_version.py
jupytercad_app/cadapp.py
jupytercad_app/utils.py
jupytercad_app/schemas/@jupyterlab/application-extension/commands.json
jupytercad_app/schemas/@jupyterlab/application-extension/context-menu.json
jupytercad_app/schemas/@jupyterlab/application-extension/package.json.orig
jupytercad_app/schemas/@jupyterlab/application-extension/property-inspector.json
jupytercad_app/schemas/@jupyterlab/application-extension/shell.json
jupytercad_app/schemas/@jupyterlab/application-extension/top-bar.json
jupytercad_app/schemas/@jupyterlab/apputils-extension/kernels-settings.json
jupytercad_app/schemas/@jupyterlab/apputils-extension/notification.json
jupytercad_app/schemas/@jupyterlab/apputils-extension/package.json.orig
jupytercad_app/schemas/@jupyterlab/apputils-extension/palette.json
jupytercad_app/schemas/@jupyterlab/apputils-extension/print.json
jupytercad_app/schemas/@jupyterlab/apputils-extension/sanitizer.json
jupytercad_app/schemas/@jupyterlab/apputils-extension/sessionDialogs.json
jupytercad_app/schemas/@jupyterlab/apputils-extension/themes.json
jupytercad_app/schemas/@jupyterlab/apputils-extension/utilityCommands.json
jupytercad_app/schemas/@jupyterlab/codemirror-extension/package.json.orig
jupytercad_app/schemas/@jupyterlab/codemirror-extension/plugin.json
jupytercad_app/schemas/@jupyterlab/completer-extension/inline-completer.json
jupytercad_app/schemas/@jupyterlab/completer-extension/manager.json
jupytercad_app/schemas/@jupyterlab/completer-extension/package.json.orig
jupytercad_app/schemas/@jupyterlab/console-extension/completer.json
jupytercad_app/schemas/@jupyterlab/console-extension/foreign.json
jupytercad_app/schemas/@jupyterlab/console-extension/package.json.orig
jupytercad_app/schemas/@jupyterlab/console-extension/tracker.json
jupytercad_app/schemas/@jupyterlab/docmanager-extension/download.json
jupytercad_app/schemas/@jupyterlab/docmanager-extension/package.json.orig
jupytercad_app-3.4.0.dist-info/METADATA
jupytercad_app-3.4.0.dist-info/WHEEL
jupytercad_app-3.4.0.dist-info/entry_points.txt
jupytercad_app-3.4.0.dist-info/licenses/LICENSE
jupytercad_app-3.4.0.dist-info/RECORD
